gandol2_ocr/__init__.py
gandol2_ocr/ocr.py
gandol2_ocr/splitter.py
gandol2_ocr/image_ocr/__init__.py
gandol2_ocr/image_ocr/cli.py
gandol2_ocr/image_ocr/ocr.py
gandol2_ocr/splitter/__init__.py
gandol2_ocr/splitter/splitter.py
gandol2_ocr-0.0.4.dist-info/METADATA
gandol2_ocr-0.0.4.dist-info/WHEEL
gandol2_ocr-0.0.4.dist-info/top_level.txt
gandol2_ocr-0.0.4.dist-info/RECORD
