Metadata-Version: 2.4
Name: gandol2-ocr
Version: 0.0.4
Summary: 이미지를 시각적 경계 기준으로 안전하게 섹션 분리 & OCR (Korean, Chinese)
Author-email: gandol2 <sskim2333@gmail.com>
License: MIT
Project-URL: Homepage, https://github.com/gandol2/gandol2-ocr
Project-URL: Repository, https://github.com/gandol2/gandol2-ocr
Project-URL: Documentation, https://github.com/gandol2/gandol2-ocr#readme
Keywords: image,section,split,opencv,computer-vision
Requires-Python: <3.13,>=3.9
Requires-Dist: paddleocr>=3.2.0
Requires-Dist: scipy>=1.13.1
Requires-Dist: matplotlib>=3.9.4
Requires-Dist: pandas>=2.3.3
Requires-Dist: opencv-python>=4.12.0.88
Provides-Extra: gpu
Requires-Dist: paddlepaddle-gpu==3.2.0; extra == "gpu"
